pkg/__init__.py
pkg/dev.py
py3_calendar-0.0.1.dist-info/METADATA
py3_calendar-0.0.1.dist-info/WHEEL
py3_calendar-0.0.1.dist-info/licenses/LICENSE
py3_calendar-0.0.1.dist-info/RECORD
