Metadata-Version: 2.1
Name: py3-calendar
Version: 0.0.1
Summary: A Calendar package.
Project-URL: Homepage, https://github.com/RayaanKhanGH/calendar
Project-URL: Bug Tracker, https://github.com/RayaanKhanGH/calendar/issues
Author: Rayaan Khan
License-File: LICENSE
Classifier: License :: OSI Approved :: MIT License
Classifier: Operating System :: OS Independent
Classifier: Programming Language :: Python :: 3
Requires-Python: >=3.7
